MANIFEST.in
README.md
setup.cfg
setup.py
filebrowser_safe_mixin_qiniu/__init__.py
filebrowser_safe_mixin_qiniu/storage.py
filebrowser_safe_mixin_qiniu.egg-info/PKG-INFO
filebrowser_safe_mixin_qiniu.egg-info/SOURCES.txt
filebrowser_safe_mixin_qiniu.egg-info/dependency_links.txt
filebrowser_safe_mixin_qiniu.egg-info/not-zip-safe
filebrowser_safe_mixin_qiniu.egg-info/requires.txt
filebrowser_safe_mixin_qiniu.egg-info/top_level.txt