Metadata-Version: 1.0
Name: filebrowser-safe-mixin-qiniu
Version: 0.1.1
Summary: Contain QiniuStorageMixin, which makes filebrowser_safe compatible with Qiniu
Home-page: http://github.com/leoleozhu/filebrowser-safe-mixin-qiniu
Author: Leo Zhu
Author-email: leiping.zhu@gmail.com
License: UNKNOWN
Platform: UNKNOWN
